{
  "__OBJECTS__": {
    "7ee99012-2f52-432f-aa4f-8f3e96ef6823": {
      "attributes": {
        "name": "Metronome",
        "TimeRegulating": "true",
        "TimeConstrained": "true",
        "Step": "1.0",
        "Meld": "false",
        "Lookahead": "0.2",
        "InstantiationScript": "",
        "GeneratorClass": "",
        "FederateType": "1",
        "EnableROAsynchronousDelivery": "true"
      },
      "__FEDERATE_BASE__": "JavaFederate",
      "federates": [],
      "__FEDERATE_TYPE__": "directly deployable",
      "parameters": [],
      "inputs": [],
      "outputs": [
        {
          "GUID": "7f759f9a-58cc-431a-a641-868125c6ca00"
        }
      ],
      "objectinputs": [],
      "objectoutputs": [],
      "RegistryInfo": "",
      "documentation": "No documentation exists yet.",
      "repository": "No repository exists yet.",
      "GUID": "7ee99012-2f52-432f-aa4f-8f3e96ef6823"
    },
    "49318f7e-1bed-4a64-a62b-775af3475158": {
      "attributes": {
        "name": "InteractionRoot",
        "Order": "timestamp",
        "LogLevel": "NORMAL",
        "EnableLogging": "false",
        "Delivery": "reliable"
      },
      "__INTERACTION_BASE__": {
        "GUID": "276a5385-fd6b-47c0-8fa0-60073ecaf3a2"
      },
      "parameters": [],
      "GUID": "49318f7e-1bed-4a64-a62b-775af3475158"
    },
    "5bf4c1d9-302c-49f2-9128-f5f8fd89bb9d": {
      "attributes": {
        "name": "C2WInteractionRoot",
        "Order": "timestamp",
        "LogLevel": "NORMAL",
        "EnableLogging": "false",
        "Delivery": "reliable"
      },
      "__INTERACTION_BASE__": {
        "GUID": "49318f7e-1bed-4a64-a62b-775af3475158"
      },
      "parameters": [
        {
          "name": "originFed",
          "ParameterType": "String",
          "Hidden": "false"
        },
        {
          "name": "sourceFed",
          "ParameterType": "String",
          "Hidden": "false"
        },
        {
          "name": "actualLogicalGenerationTime",
          "ParameterType": "double",
          "Hidden": "false"
        },
        {
          "name": "federateFilter",
          "ParameterType": "String",
          "Hidden": "false"
        }
      ],
      "GUID": "5bf4c1d9-302c-49f2-9128-f5f8fd89bb9d"
    },
    "7f759f9a-58cc-431a-a641-868125c6ca00": {
      "attributes": {
        "name": "SimTime",
        "Order": "timestamp",
        "LogLevel": "NORMAL",
        "EnableLogging": "false",
        "Delivery": "reliable"
      },
      "__INTERACTION_BASE__": {
        "GUID": "5bf4c1d9-302c-49f2-9128-f5f8fd89bb9d"
      },
      "parameters": [
        {
          "name": "startTime",
          "ParameterType": "double",
          "Hidden": "false"
        },
        {
          "name": "originFed",
          "ParameterType": "String",
          "Hidden": "false"
        },
        {
          "name": "sourceFed",
          "ParameterType": "String",
          "Hidden": "false"
        },
        {
          "name": "stopTime",
          "ParameterType": "double",
          "Hidden": "false"
        },
        {
          "name": "ignoreTil",
          "ParameterType": "double",
          "Hidden": "false"
        },
        {
          "name": "secondsPerLogicalTime",
          "ParameterType": "double",
          "Hidden": "false"
        },
        {
          "name": "actualLogicalGenerationTime",
          "ParameterType": "double",
          "Hidden": "false"
        },
        {
          "name": "federateFilter",
          "ParameterType": "String",
          "Hidden": "false"
        }
      ],
      "GUID": "7f759f9a-58cc-431a-a641-868125c6ca00"
    }
  },
  "__ROOT_OBJECT__": {
    "GUID": "7ee99012-2f52-432f-aa4f-8f3e96ef6823",
    "name": "Metronome",
    "version": "0.0.1",
    "description": ""
  },
  "Federates": {
    "7ee99012-2f52-432f-aa4f-8f3e96ef6823": ""
  },
  "COAs": {},
  "Experiments": {},
  "Interactions": {
    "49318f7e-1bed-4a64-a62b-775af3475158": "",
    "5bf4c1d9-302c-49f2-9128-f5f8fd89bb9d": "",
    "7f759f9a-58cc-431a-a641-868125c6ca00": ""
  },
  "Objects": {},
  "ObjectAttribute": {},
  "Repositories": [],
  "Builds": [],
  "Executions": []
}